README.md
setup.py
the_video_editaneitor.egg-info/PKG-INFO
the_video_editaneitor.egg-info/SOURCES.txt
the_video_editaneitor.egg-info/dependency_links.txt
the_video_editaneitor.egg-info/top_level.txt
the_videoeditaneitor/__init__.py
the_videoeditaneitor/src/__init__.py
the_videoeditaneitor/src/start.py
the_videoeditaneitor/src/modules/__init__.py
the_videoeditaneitor/src/modules/menuModule.py
the_videoeditaneitor/src/modules/videoFileRowModule.py
the_videoeditaneitor/src/modules/videoFilesModule.py
the_videoeditaneitor/src/modules/videoModule.py