Metadata-Version: 2.1
Name: the-video-editaneitor
Version: 0.0.2
Summary: This is a small video clips editor
Home-page: https://github.com/pypa/sampleproject
Author: Demian Bolivar
Author-email: demian054m@gmail.com
License: UNKNOWN
Platform: UNKNOWN
Classifier: Programming Language :: Python :: 3
Classifier: License :: OSI Approved :: MIT License
Classifier: Operating System :: OS Independent
Requires-Python: >=3.6
